wyper/__init__.py
wyper/colors.py
wyper/fonts/dmsans-bold.ttf
wyper/fonts/dmsans-medium.ttf
wyper/fonts/dmsans-thin.ttf
wyper/fonts/material-symbols-round.ttf
wyper/layouthandler.py
wyper/widgets.py
wyper-0.1.2.dist-info/LICENSE
wyper-0.1.2.dist-info/METADATA
wyper-0.1.2.dist-info/WHEEL
wyper-0.1.2.dist-info/RECORD
