Metadata-Version: 2.1
Name: wyper
Version: 0.1.2
Summary: A First Class GUI Library inspired by flutter
License: MIT
Author: Amaan
Author-email: 71920621+amaank404@users.noreply.github.com
Requires-Python: >=3.8,<4.0
Classifier: License :: OSI Approved :: MIT License
Classifier: Programming Language :: Python :: 3
Classifier: Programming Language :: Python :: 3.8
Classifier: Programming Language :: Python :: 3.9
Classifier: Programming Language :: Python :: 3.10
Classifier: Programming Language :: Python :: 3.11
Requires-Dist: pillow (>=10,<11)
Requires-Dist: pygame (>=2,<3)
